xgaproxy/__init__.py
xgaproxy/a2a_tool_proxy_app.py
xgaproxy/tool_base.py
xgaproxy/a2a/base.py
xgaproxy/a2a/config.py
xgaproxy/a2a/helper.py
xgaproxy/utils/setup_env.py
xgaproxy-0.1.3.dist-info/METADATA
xgaproxy-0.1.3.dist-info/WHEEL
xgaproxy-0.1.3.dist-info/entry_points.txt
xgaproxy-0.1.3.dist-info/RECORD
