Metadata-Version: 2.4
Name: xgaproxy
Version: 0.1.3
Summary: Extreme Agent Tool Proxy
Requires-Python: >=3.11
Requires-Dist: a2a-sdk==0.3.3
Requires-Dist: colorlog==6.9.0
Requires-Dist: mcp==1.13.0
Requires-Dist: pyyaml==6.0.2
